pkg_alm2/IoT.csv
pkg_alm2/LM_hor_shift.h
pkg_alm2/LM_time_lib.c
pkg_alm2/LM_time_lib.so
pkg_alm2/LogL-global-v5.py
pkg_alm2/TCP.csv
pkg_alm2/TIP.csv
pkg_alm2/__init__.py
pkg_alm2/all_fix_counts.csv
pkg_alm2/auto.csv
pkg_alm2/bernreal-100.txt
pkg_alm2/bernreal-norm-100-digamma.txt
pkg_alm2/bernreal-norm-100.txt
pkg_alm2/cane.csv
pkg_alm2/cavallo.csv
pkg_alm2/constants_hor_shift.h
pkg_alm2/err_coeff-100.txt
pkg_alm2/err_coeff-100_digamma.txt
pkg_alm2/err_coeff-100_trigamma.txt
pkg_alm2/executor.py
pkg_alm2/f_vs_m.csv
pkg_alm2/init_hor_shift.h
pkg_alm2/makefile
pkg_alm2/mideast.csv
pkg_alm2/scrambler.py
pkg_alm2/space.csv
pkg_alm2/test_fix_counts.csv
pkg_alm2-1.0.3.dist-info/METADATA
pkg_alm2-1.0.3.dist-info/WHEEL
pkg_alm2-1.0.3.dist-info/RECORD
