Metadata-Version: 2.1
Name: pkg-alm2
Version: 1.0.3
Summary: Python C-wrapped implementation of the LM technique for computing the log-likelihood function of the Dirichlet Mutlinomial Distribution with comparison to Python math and scipy implementations of the same function
Author: Sherenaz Al-Haj Baddar(s.baddar AT ju.edu.jo),Alessandro Languasco(alessandro.languasco AT unipd.it),Mauro Migliardi(mauro.migliardi AT unipd.it)
Author-email: s.baddar@ju.edu.jo
Requires-Python: >=3.11
Classifier: Programming Language :: Python :: 3
Classifier: Programming Language :: Python :: 3.11
Classifier: Programming Language :: Python :: 3.12
